CHANGES.md
MANIFEST.in
README.md
setup.py
djangocms_livedraftswitch/__init__.py
djangocms_livedraftswitch.egg-info/PKG-INFO
djangocms_livedraftswitch.egg-info/SOURCES.txt
djangocms_livedraftswitch.egg-info/dependency_links.txt
djangocms_livedraftswitch.egg-info/top_level.txt
djangocms_livedraftswitch/static/djangocms_livedraftswitch/toggle-switch.css
djangocms_livedraftswitch/templates/cms/toolbar/toolbar_javascript.html