Metadata-Version: 1.1
Name: djangocms-livedraftswitch
Version: 0.2.3
Summary: Returns classic DjangoCMS-style live-draft switch to DjangoCMS
Home-page: https://github.com/frnhr/djangocms-livedraftswitch/
Author: Fran Hrzenjak
Author-email: fran.hrzenjak@gmail.com
License: The Unlicense
Platform: any
Classifier: Development Status :: 4 - Beta
Classifier: Environment :: Web Environment
Classifier: Framework :: Django
Classifier: Intended Audience :: Developers
Classifier: License :: Public Domain
Classifier: Operating System :: OS Independent
Classifier: Programming Language :: Python
Classifier: Topic :: Utilities
